update_cache/__init__.py
update_cache/admin.py
update_cache/apps.py
update_cache/brokers.py
update_cache/decorators.py
update_cache/models.py
update_cache/settings.py
update_cache/utils.py
update_cache/version.py
update_cache/cache/__init__.py
update_cache/cache/cache.py
update_cache/cache/registry.py
update_cache/cache/update.py
update_cache/cache/views.py
update_cache/migrations/0001_initial.py
update_cache/migrations/__init__.py
django_update_cache-1.0.6.dist-info/METADATA
django_update_cache-1.0.6.dist-info/WHEEL
django_update_cache-1.0.6.dist-info/top_level.txt
django_update_cache-1.0.6.dist-info/RECORD
