Metadata-Version: 2.1
Name: django-update-cache
Version: 1.0.6
Summary: Lazy cache updates for Django
Home-page: https://github.com/bboogaard/django-update-cache
Author: Bram Boogaard
Author-email: padawan@hetnet.nl
License: MIT License
Keywords: Django Update cache
Classifier: Development Status :: 3 - Alpha
Requires-Dist: django ~=4.2.7
Requires-Dist: django-rq ~=2.8.1
